langchain_parrot_link/__init__.py
langchain_parrot_link/chat_models.py
langchain_parrot_link-0.1.0.dist-info/METADATA
langchain_parrot_link-0.1.0.dist-info/WHEEL
langchain_parrot_link-0.1.0.dist-info/RECORD
